{
	"info": {
		"_postman_id": "0987370c-c531-485b-a192-f04c4d284fea",
		"name": "User",
		"schema": "https://schema.getpostman.com/json/collection/v2.1.0/collection.json",
		"_exporter_id": "36939501"
	},
	"item": [
		{
			"name": "Register",
			"request": {
				"method": "POST",
				"header": [],
				"body": {
					"mode": "raw",
					"raw": "{\r\n    \"name\": \"Henry\",\r\n    \"email\": \"henryasante2336@gmail.com\",\r\n    \"password\": \"test123\"\r\n}",
					"options": {
						"raw": {
							"language": "json"
						}
					}
				},
				"url": {
					"raw": "{{Base_URL}}/register",
					"host": [
						"{{Base_URL}}"
					],
					"path": [
						"register"
					]
				}
			},
			"response": []
		},
		{
			"name": "Login",
			"request": {
				"method": "POST",
				"header": [],
				"body": {
					"mode": "raw",
					"raw": "{\r\n    \"email\": \"henryasante336@gmail.com\",\r\n    \"password\": \"test123\"\r\n}",
					"options": {
						"raw": {
							"language": "json"
						}
					}
				},
				"url": {
					"raw": "{{Base_URL}}/login",
					"host": [
						"{{Base_URL}}"
					],
					"path": [
						"login"
					]
				}
			},
			"response": []
		}
	]
}